[
  {
    "ContainingType": "WEB_API.Controllers.ClientesController",
    "Method": "Get",
    "RelativePath": "api/Clientes/buscar / {clienteID}",
    "HttpMethod": "GET",
    "IsController": true,
    "Order": 0,
    "Parameters": [
      {
        "Name": "clienteID",
        "Type": "System.Int32",
        "IsRequired": true
      }
    ],
    "ReturnTypes": [
      {
        "Type": "WEB_API.DTOs.ClientesDTO",
        "MediaTypes": [
          "text/plain",
          "application/json",
          "text/json"
        ],
        "StatusCode": 200
      }
    ]
  },
  {
    "ContainingType": "WEB_API.Controllers.ClientesController",
    "Method": "Editar",
    "RelativePath": "api/Clientes/editar",
    "HttpMethod": "PUT",
    "IsController": true,
    "Order": 0,
    "Parameters": [
      {
        "Name": "clientesDTO",
        "Type": "WEB_API.DTOs.ClientesDTO",
        "IsRequired": true
      }
    ],
    "ReturnTypes": [
      {
        "Type": "WEB_API.DTOs.ClientesDTO",
        "MediaTypes": [
          "text/plain",
          "application/json",
          "text/json"
        ],
        "StatusCode": 200
      }
    ]
  },
  {
    "ContainingType": "WEB_API.Controllers.ClientesController",
    "Method": "Eliminar",
    "RelativePath": "api/Clientes/eliminar / {clientID}",
    "HttpMethod": "DELETE",
    "IsController": true,
    "Order": 0,
    "Parameters": [
      {
        "Name": "clientID",
        "Type": "System.Int32",
        "IsRequired": true
      }
    ],
    "ReturnTypes": [
      {
        "Type": "WEB_API.DTOs.ClientesDTO",
        "MediaTypes": [
          "text/plain",
          "application/json",
          "text/json"
        ],
        "StatusCode": 200
      }
    ]
  },
  {
    "ContainingType": "WEB_API.Controllers.ClientesController",
    "Method": "Guardar",
    "RelativePath": "api/Clientes/guardar",
    "HttpMethod": "POST",
    "IsController": true,
    "Order": 0,
    "Parameters": [
      {
        "Name": "clientesDTO",
        "Type": "WEB_API.DTOs.ClientesDTO",
        "IsRequired": true
      }
    ],
    "ReturnTypes": [
      {
        "Type": "WEB_API.DTOs.ClientesDTO",
        "MediaTypes": [
          "text/plain",
          "application/json",
          "text/json"
        ],
        "StatusCode": 200
      }
    ]
  },
  {
    "ContainingType": "WEB_API.Controllers.ClientesController",
    "Method": "Get",
    "RelativePath": "api/Clientes/lista",
    "HttpMethod": "GET",
    "IsController": true,
    "Order": 0,
    "Parameters": [],
    "ReturnTypes": [
      {
        "Type": "System.Collections.Generic.List\u00601[[WEB_API.DTOs.ClientesDTO, WEB API, Version=1.0.0.0, Culture=neutral, PublicKeyToken=null]]",
        "MediaTypes": [
          "text/plain",
          "application/json",
          "text/json"
        ],
        "StatusCode": 200
      }
    ]
  },
  {
    "ContainingType": "WEB_API.Controllers.RolesController",
    "Method": "Get",
    "RelativePath": "api/Roles/buscar / {rolID}",
    "HttpMethod": "GET",
    "IsController": true,
    "Order": 0,
    "Parameters": [
      {
        "Name": "rolID",
        "Type": "System.Int32",
        "IsRequired": true
      }
    ],
    "ReturnTypes": [
      {
        "Type": "WEB_API.DTOs.RolesDTO",
        "MediaTypes": [
          "text/plain",
          "application/json",
          "text/json"
        ],
        "StatusCode": 200
      }
    ]
  },
  {
    "ContainingType": "WEB_API.Controllers.RolesController",
    "Method": "Editar",
    "RelativePath": "api/Roles/editar",
    "HttpMethod": "PUT",
    "IsController": true,
    "Order": 0,
    "Parameters": [
      {
        "Name": "rolesDTO",
        "Type": "WEB_API.DTOs.RolesDTO",
        "IsRequired": true
      }
    ],
    "ReturnTypes": [
      {
        "Type": "WEB_API.DTOs.RolesDTO",
        "MediaTypes": [
          "text/plain",
          "application/json",
          "text/json"
        ],
        "StatusCode": 200
      }
    ]
  },
  {
    "ContainingType": "WEB_API.Controllers.RolesController",
    "Method": "Eliminar",
    "RelativePath": "api/Roles/eliminar / {rolID}",
    "HttpMethod": "DELETE",
    "IsController": true,
    "Order": 0,
    "Parameters": [
      {
        "Name": "rolID",
        "Type": "System.Int32",
        "IsRequired": true
      }
    ],
    "ReturnTypes": [
      {
        "Type": "WEB_API.DTOs.RolesDTO",
        "MediaTypes": [
          "text/plain",
          "application/json",
          "text/json"
        ],
        "StatusCode": 200
      }
    ]
  },
  {
    "ContainingType": "WEB_API.Controllers.RolesController",
    "Method": "Guardar",
    "RelativePath": "api/Roles/guardar",
    "HttpMethod": "POST",
    "IsController": true,
    "Order": 0,
    "Parameters": [
      {
        "Name": "rolesDTO",
        "Type": "WEB_API.DTOs.RolesDTO",
        "IsRequired": true
      }
    ],
    "ReturnTypes": [
      {
        "Type": "WEB_API.DTOs.RolesDTO",
        "MediaTypes": [
          "text/plain",
          "application/json",
          "text/json"
        ],
        "StatusCode": 200
      }
    ]
  },
  {
    "ContainingType": "WEB_API.Controllers.RolesController",
    "Method": "Get",
    "RelativePath": "api/Roles/lista",
    "HttpMethod": "GET",
    "IsController": true,
    "Order": 0,
    "Parameters": [],
    "ReturnTypes": [
      {
        "Type": "System.Collections.Generic.List\u00601[[WEB_API.DTOs.RolesDTO, WEB API, Version=1.0.0.0, Culture=neutral, PublicKeyToken=null]]",
        "MediaTypes": [
          "text/plain",
          "application/json",
          "text/json"
        ],
        "StatusCode": 200
      }
    ]
  },
  {
    "ContainingType": "WEB_API.Controllers.SolicitudesCambioContrase\u00F1aController",
    "Method": "Get",
    "RelativePath": "api/SolicitudesCambioContrase\u00F1a/buscar / {solicitudID}",
    "HttpMethod": "GET",
    "IsController": true,
    "Order": 0,
    "Parameters": [
      {
        "Name": "solicitudID",
        "Type": "System.Int32",
        "IsRequired": true
      }
    ],
    "ReturnTypes": [
      {
        "Type": "WEB_API.DTOs.SolicitudesCambioContrase\u00F1aDTO",
        "MediaTypes": [
          "text/plain",
          "application/json",
          "text/json"
        ],
        "StatusCode": 200
      }
    ]
  },
  {
    "ContainingType": "WEB_API.Controllers.SolicitudesCambioContrase\u00F1aController",
    "Method": "Editar",
    "RelativePath": "api/SolicitudesCambioContrase\u00F1a/editar",
    "HttpMethod": "PUT",
    "IsController": true,
    "Order": 0,
    "Parameters": [
      {
        "Name": "solicitudesCambioContrase\u00F1aDTO",
        "Type": "WEB_API.DTOs.SolicitudesCambioContrase\u00F1aDTO",
        "IsRequired": true
      }
    ],
    "ReturnTypes": [
      {
        "Type": "WEB_API.DTOs.SolicitudesCambioContrase\u00F1aDTO",
        "MediaTypes": [
          "text/plain",
          "application/json",
          "text/json"
        ],
        "StatusCode": 200
      }
    ]
  },
  {
    "ContainingType": "WEB_API.Controllers.SolicitudesCambioContrase\u00F1aController",
    "Method": "Eliminar",
    "RelativePath": "api/SolicitudesCambioContrase\u00F1a/eliminar / {solicitudesID}",
    "HttpMethod": "DELETE",
    "IsController": true,
    "Order": 0,
    "Parameters": [
      {
        "Name": "solicitudesID",
        "Type": "System.Int32",
        "IsRequired": true
      }
    ],
    "ReturnTypes": [
      {
        "Type": "WEB_API.DTOs.SolicitudesCambioContrase\u00F1aDTO",
        "MediaTypes": [
          "text/plain",
          "application/json",
          "text/json"
        ],
        "StatusCode": 200
      }
    ]
  },
  {
    "ContainingType": "WEB_API.Controllers.SolicitudesCambioContrase\u00F1aController",
    "Method": "Guardar",
    "RelativePath": "api/SolicitudesCambioContrase\u00F1a/guardar",
    "HttpMethod": "POST",
    "IsController": true,
    "Order": 0,
    "Parameters": [
      {
        "Name": "solicitudesCambioContrase\u00F1aDTO",
        "Type": "WEB_API.DTOs.SolicitudesCambioContrase\u00F1aDTO",
        "IsRequired": true
      }
    ],
    "ReturnTypes": [
      {
        "Type": "WEB_API.DTOs.SolicitudesCambioContrase\u00F1aDTO",
        "MediaTypes": [
          "text/plain",
          "application/json",
          "text/json"
        ],
        "StatusCode": 200
      }
    ]
  },
  {
    "ContainingType": "WEB_API.Controllers.SolicitudesCambioContrase\u00F1aController",
    "Method": "Get",
    "RelativePath": "api/SolicitudesCambioContrase\u00F1a/lista",
    "HttpMethod": "GET",
    "IsController": true,
    "Order": 0,
    "Parameters": [],
    "ReturnTypes": [
      {
        "Type": "System.Collections.Generic.List\u00601[[WEB_API.DTOs.SolicitudesCambioContrase\u00F1aDTO, WEB API, Version=1.0.0.0, Culture=neutral, PublicKeyToken=null]]",
        "MediaTypes": [
          "text/plain",
          "application/json",
          "text/json"
        ],
        "StatusCode": 200
      }
    ]
  },
  {
    "ContainingType": "WEB_API.Controllers.UsuarioController",
    "Method": "Get",
    "RelativePath": "api/Usuario/buscar / {usuarioID}",
    "HttpMethod": "GET",
    "IsController": true,
    "Order": 0,
    "Parameters": [
      {
        "Name": "usuarioID",
        "Type": "System.Int32",
        "IsRequired": true
      }
    ],
    "ReturnTypes": [
      {
        "Type": "WEB_API.DTOs.UsuarioDTO",
        "MediaTypes": [
          "text/plain",
          "application/json",
          "text/json"
        ],
        "StatusCode": 200
      }
    ]
  },
  {
    "ContainingType": "WEB_API.Controllers.UsuarioController",
    "Method": "Editar",
    "RelativePath": "api/Usuario/editar",
    "HttpMethod": "PUT",
    "IsController": true,
    "Order": 0,
    "Parameters": [
      {
        "Name": "usuarioDTO",
        "Type": "WEB_API.DTOs.UsuarioDTO",
        "IsRequired": true
      }
    ],
    "ReturnTypes": [
      {
        "Type": "WEB_API.DTOs.UsuarioDTO",
        "MediaTypes": [
          "text/plain",
          "application/json",
          "text/json"
        ],
        "StatusCode": 200
      }
    ]
  },
  {
    "ContainingType": "WEB_API.Controllers.UsuarioController",
    "Method": "Eliminar",
    "RelativePath": "api/Usuario/eliminar / {usuarioID}",
    "HttpMethod": "DELETE",
    "IsController": true,
    "Order": 0,
    "Parameters": [
      {
        "Name": "usuarioID",
        "Type": "System.Int32",
        "IsRequired": true
      }
    ],
    "ReturnTypes": [
      {
        "Type": "WEB_API.DTOs.UsuarioDTO",
        "MediaTypes": [
          "text/plain",
          "application/json",
          "text/json"
        ],
        "StatusCode": 200
      }
    ]
  },
  {
    "ContainingType": "WEB_API.Controllers.UsuarioController",
    "Method": "Guardar",
    "RelativePath": "api/Usuario/guardar",
    "HttpMethod": "POST",
    "IsController": true,
    "Order": 0,
    "Parameters": [
      {
        "Name": "usuarioDTO",
        "Type": "WEB_API.DTOs.UsuarioDTO",
        "IsRequired": true
      }
    ],
    "ReturnTypes": [
      {
        "Type": "WEB_API.DTOs.UsuarioDTO",
        "MediaTypes": [
          "text/plain",
          "application/json",
          "text/json"
        ],
        "StatusCode": 200
      }
    ]
  },
  {
    "ContainingType": "WEB_API.Controllers.UsuarioController",
    "Method": "Get",
    "RelativePath": "api/Usuario/lista",
    "HttpMethod": "GET",
    "IsController": true,
    "Order": 0,
    "Parameters": [],
    "ReturnTypes": [
      {
        "Type": "System.Collections.Generic.List\u00601[[WEB_API.DTOs.UsuarioDTO, WEB API, Version=1.0.0.0, Culture=neutral, PublicKeyToken=null]]",
        "MediaTypes": [
          "text/plain",
          "application/json",
          "text/json"
        ],
        "StatusCode": 200
      }
    ]
  },
  {
    "ContainingType": "WEB_API.Controllers.UsuarioRolController",
    "Method": "Get",
    "RelativePath": "api/UsuarioRol/buscar / {usuarioRolID}",
    "HttpMethod": "GET",
    "IsController": true,
    "Order": 0,
    "Parameters": [
      {
        "Name": "usuarioRolID",
        "Type": "System.Int32",
        "IsRequired": true
      }
    ],
    "ReturnTypes": [
      {
        "Type": "WEB_API.DTOs.UsuarioRolDTO",
        "MediaTypes": [
          "text/plain",
          "application/json",
          "text/json"
        ],
        "StatusCode": 200
      }
    ]
  },
  {
    "ContainingType": "WEB_API.Controllers.UsuarioRolController",
    "Method": "Editar",
    "RelativePath": "api/UsuarioRol/editar",
    "HttpMethod": "PUT",
    "IsController": true,
    "Order": 0,
    "Parameters": [
      {
        "Name": "usuarioRolDTO",
        "Type": "WEB_API.DTOs.UsuarioRolDTO",
        "IsRequired": true
      }
    ],
    "ReturnTypes": [
      {
        "Type": "WEB_API.DTOs.UsuarioRolDTO",
        "MediaTypes": [
          "text/plain",
          "application/json",
          "text/json"
        ],
        "StatusCode": 200
      }
    ]
  },
  {
    "ContainingType": "WEB_API.Controllers.UsuarioRolController",
    "Method": "Eliminar",
    "RelativePath": "api/UsuarioRol/eliminar / {usuarioRolID}",
    "HttpMethod": "DELETE",
    "IsController": true,
    "Order": 0,
    "Parameters": [
      {
        "Name": "usuarioRolID",
        "Type": "System.Int32",
        "IsRequired": true
      }
    ],
    "ReturnTypes": [
      {
        "Type": "WEB_API.DTOs.UsuarioRolDTO",
        "MediaTypes": [
          "text/plain",
          "application/json",
          "text/json"
        ],
        "StatusCode": 200
      }
    ]
  },
  {
    "ContainingType": "WEB_API.Controllers.UsuarioRolController",
    "Method": "Guardar",
    "RelativePath": "api/UsuarioRol/guardar",
    "HttpMethod": "POST",
    "IsController": true,
    "Order": 0,
    "Parameters": [
      {
        "Name": "usuarioRolDTO",
        "Type": "WEB_API.DTOs.UsuarioRolDTO",
        "IsRequired": true
      }
    ],
    "ReturnTypes": [
      {
        "Type": "WEB_API.DTOs.UsuarioRolDTO",
        "MediaTypes": [
          "text/plain",
          "application/json",
          "text/json"
        ],
        "StatusCode": 200
      }
    ]
  },
  {
    "ContainingType": "WEB_API.Controllers.UsuarioRolController",
    "Method": "Get",
    "RelativePath": "api/UsuarioRol/lista",
    "HttpMethod": "GET",
    "IsController": true,
    "Order": 0,
    "Parameters": [],
    "ReturnTypes": [
      {
        "Type": "System.Collections.Generic.List\u00601[[WEB_API.DTOs.UsuarioRolDTO, WEB API, Version=1.0.0.0, Culture=neutral, PublicKeyToken=null]]",
        "MediaTypes": [
          "text/plain",
          "application/json",
          "text/json"
        ],
        "StatusCode": 200
      }
    ]
  },
  {
    "ContainingType": "WEB_API.Controllers.WeatherForecastController",
    "Method": "Get",
    "RelativePath": "WeatherForecast",
    "HttpMethod": "GET",
    "IsController": true,
    "Order": 0,
    "Parameters": [],
    "ReturnTypes": [
      {
        "Type": "System.Collections.Generic.IEnumerable\u00601[[WEB_API.WeatherForecast, WEB API, Version=1.0.0.0, Culture=neutral, PublicKeyToken=null]]",
        "MediaTypes": [
          "text/plain",
          "application/json",
          "text/json"
        ],
        "StatusCode": 200
      }
    ],
    "EndpointName": "GetWeatherForecast"
  }
]